wagtail_simple_gallery/__init__.py
wagtail_simple_gallery/apps.py
wagtail_simple_gallery/models.py
wagtail_simple_gallery/tests.py
wagtail_simple_gallery/urls.py
wagtail_simple_gallery/views.py
wagtail_simple_gallery/wagtail_hooks.py
wagtail_simple_gallery/locale/fr/LC_MESSAGES/django.mo
wagtail_simple_gallery/locale/fr/LC_MESSAGES/django.po
wagtail_simple_gallery/migrations/0001_initial.py
wagtail_simple_gallery/migrations/0002_auto_20170309_1046.py
wagtail_simple_gallery/migrations/0003_simplegalleryindex_order_images_by.py
wagtail_simple_gallery/migrations/__init__.py
wagtail_simple_gallery/static/css/baguetteBox.min.css
wagtail_simple_gallery/static/css/simple-gallery-admin.css
wagtail_simple_gallery/static/css/simple-gallery.css
wagtail_simple_gallery/static/js/baguetteBox.min.js
wagtail_simple_gallery/templates/simple_gallery_base.html
wagtail_simple_gallery/templates/wagtail_simple_gallery/simple_gallery.html
wagtail_simple_gallery/templates/wagtail_simple_gallery/simple_gallery_index.html
wagtail_simple_gallery/templatetags/__init__.py
wagtail_simple_gallery/templatetags/wagtailsimplegallery_tags.py
wagtail_simple_gallery-0.6.4.dist-info/LICENSE.txt
wagtail_simple_gallery-0.6.4.dist-info/METADATA
wagtail_simple_gallery-0.6.4.dist-info/WHEEL
wagtail_simple_gallery-0.6.4.dist-info/top_level.txt
wagtail_simple_gallery-0.6.4.dist-info/RECORD
