Metadata-Version: 2.1
Name: wagtail-simple-gallery
Version: 0.6.4
Summary: A simple gallery app for Wagtail.
Home-page: https://github.com/temeez/wagtail-simple-gallery
Author: Teemu Nieminen
Author-email: temeez.dev@gmail.com
License: MIT License
Keywords: wagtail cms model page templatetags
Platform: UNKNOWN
Classifier: Environment :: Web Environment
Classifier: Framework :: Django
Classifier: Intended Audience :: Developers
Classifier: Operating System :: OS Independent
Classifier: Programming Language :: Python :: 3
Classifier: Topic :: Internet :: WWW/HTTP
Classifier: Topic :: Internet :: WWW/HTTP :: Dynamic Content
Requires-Dist: django (>=2.0)
Requires-Dist: wagtail (<3.0,>=2.4)
